video_to_claude/__init__.py
video_to_claude/cli.py
video_to_claude/download.py
video_to_claude/mcp_server.py
video_to_claude/upload.py
video_to_claude/core/__init__.py
video_to_claude/core/audio.py
video_to_claude/core/frames.py
video_to_claude/core/manifest.py
video_to_claude/core/processor.py
video_to_claude-0.2.1.dist-info/METADATA
video_to_claude-0.2.1.dist-info/WHEEL
video_to_claude-0.2.1.dist-info/entry_points.txt
video_to_claude-0.2.1.dist-info/licenses/LICENSE
video_to_claude-0.2.1.dist-info/RECORD
