Metadata-Version: 2.4
Name: video-to-claude
Version: 0.2.1
Summary: Translate video files into a format Claude can experience - a video codec for Claude
Project-URL: Homepage, https://github.com/ai-media-tools/video-to-claude
Project-URL: Repository, https://github.com/ai-media-tools/video-to-claude
Project-URL: Issues, https://github.com/ai-media-tools/video-to-claude/issues
Author: video-to-claude contributors
License-Expression: MIT
License-File: LICENSE
Keywords: ai,audio-analysis,claude,frames,mcp,video
Classifier: Development Status :: 4 - Beta
Classifier: Environment :: Console
Classifier: Intended Audience :: Developers
Classifier: License :: OSI Approved :: MIT License
Classifier: Operating System :: OS Independent
Classifier: Programming Language :: Python :: 3
Classifier: Programming Language :: Python :: 3.10
Classifier: Programming Language :: Python :: 3.11
Classifier: Programming Language :: Python :: 3.12
Classifier: Topic :: Multimedia :: Video
Classifier: Topic :: Scientific/Engineering :: Artificial Intelligence
Requires-Python: >=3.10
Requires-Dist: click>=8.0
Requires-Dist: matplotlib>=3.7
Requires-Dist: numpy>=1.24
Requires-Dist: scipy>=1.10
Provides-Extra: all
Requires-Dist: boto3>=1.28; extra == 'all'
Requires-Dist: fastmcp>=0.1.0; extra == 'all'
Requires-Dist: yt-dlp>=2023.0.0; extra == 'all'
Provides-Extra: dev
Requires-Dist: boto3>=1.28; extra == 'dev'
Requires-Dist: fastmcp>=0.1.0; extra == 'dev'
Requires-Dist: pytest-asyncio>=0.21; extra == 'dev'
Requires-Dist: pytest>=7.0; extra == 'dev'
Requires-Dist: yt-dlp>=2023.0.0; extra == 'dev'
Provides-Extra: download
Requires-Dist: yt-dlp>=2023.0.0; extra == 'download'
Provides-Extra: mcp
Requires-Dist: fastmcp>=0.1.0; extra == 'mcp'
Provides-Extra: upload
Requires-Dist: boto3>=1.28; extra == 'upload'
